rolodex/__init__.py
rolodex/api.py
rolodex/cli.py
rolodex/io.py
rolodex/store.py
my_rolodex-0.2.0.dist-info/entry_points.txt
my_rolodex-0.2.0.dist-info/WHEEL
my_rolodex-0.2.0.dist-info/METADATA
my_rolodex-0.2.0.dist-info/RECORD
