Metadata-Version: 2.1
Name: my-rolodex
Version: 0.2.0
Summary: Animal Logic: Technical Challenge
Home-page: https://github.com/ylathouris/rolodex
License: MIT
Keywords: code-challenge
Author: Yani Lathouris
Author-email: ylathouris@gmail.com
Requires-Python: >=3.8,<4.0
Classifier: Development Status :: 3 - Alpha
Classifier: Environment :: Console
Classifier: Intended Audience :: Developers
Classifier: License :: OSI Approved :: MIT License
Classifier: Programming Language :: Python :: 3
Classifier: Programming Language :: Python :: 3.8
Classifier: Topic :: Software Development :: Libraries :: Python Modules
Requires-Dist: colorama (>=0.4.3,<0.5.0)
Requires-Dist: pydantic (>=1.5,<2.0)
Requires-Dist: pyyaml (>=5.3.1,<6.0.0)
Requires-Dist: structlog (>=20.1.0,<21.0.0)
Requires-Dist: typer (>=0.1.1,<0.2.0)
Project-URL: Repository, https://github.com/ylathouris/rolodex
